reifydb-0.0.1.dist-info/METADATA
reifydb-0.0.1.dist-info/WHEEL
reifydb/__init__.py
reifydb/__init__.pyi
reifydb/py.typed
reifydb/reifydb.abi3.so
reifydb-0.0.1.dist-info/RECORD
